mongorest/__init__.py
mongorest/collection.py
mongorest/database.py
mongorest/decorators.py
mongorest/errors.py
mongorest/middlewares.py
mongorest/resource.py
mongorest/settings.py
mongorest/testcase.py
mongorest/utils.py
mongorest/validator.py
mongorest/wrappers.py
mongorest/wsgi.py
mongorest-3.2.8.dist-info/DESCRIPTION.rst
mongorest-3.2.8.dist-info/LICENSE.txt
mongorest-3.2.8.dist-info/METADATA
mongorest-3.2.8.dist-info/RECORD
mongorest-3.2.8.dist-info/WHEEL
mongorest-3.2.8.dist-info/metadata.json
mongorest-3.2.8.dist-info/top_level.txt
