Metadata-Version: 2.0
Name: mongorest
Version: 3.2.8
Summary: Easy REST APIs using MongoDB.
Home-page: https://github.com/lvieirajr/mongorest
Author: Luis Vieira
Author-email: lvieira@lvieira.com
License: UNKNOWN
Keywords: mongodb,mongo,rest,api,pymongo,werkzeug
Platform: UNKNOWN
Classifier: Development Status :: 5 - Production/Stable
Classifier: Environment :: Web Environment
Classifier: Intended Audience :: Developers
Classifier: License :: OSI Approved :: BSD License
Classifier: Programming Language :: Python
Classifier: Programming Language :: Python :: 2
Classifier: Programming Language :: Python :: 2.7
Classifier: Programming Language :: Python :: 3
Classifier: Programming Language :: Python :: 3.3
Classifier: Programming Language :: Python :: 3.4
Classifier: Programming Language :: Python :: 3.5
Classifier: Programming Language :: Python :: Implementation :: PyPy
Classifier: Topic :: Internet :: WWW/HTTP
Classifier: Topic :: Internet :: WWW/HTTP :: Dynamic Content
Classifier: Topic :: Internet :: WWW/HTTP :: WSGI
Classifier: Topic :: Software Development :: Libraries :: Application Frameworks
Classifier: Topic :: Software Development :: Libraries :: Python Modules
Requires-Dist: cerberus (==0.9.2)
Requires-Dist: pymongo (==3.4.0)
Requires-Dist: six (==1.10.0)
Requires-Dist: werkzeug (==0.11.11)
